LICENSE
MANIFEST.in
README.md
boto.cfg.sample
ccwatch.yaml.sample
setup.py
celery_cloudwatch/__init__.py
celery_cloudwatch/__main__.py
celery_cloudwatch/__version__.py
celery_cloudwatch/camera.py
celery_cloudwatch/cloudwatch_camera.py
celery_cloudwatch/import_class.py
celery_cloudwatch/print_camera.py
celery_cloudwatch/state.py
celery_cloudwatch/stats.py
celery_cloudwatch/task_monitor.py
celery_cloudwatch.egg-info/PKG-INFO
celery_cloudwatch.egg-info/SOURCES.txt
celery_cloudwatch.egg-info/dependency_links.txt
celery_cloudwatch.egg-info/entry_points.txt
celery_cloudwatch.egg-info/requires.txt
celery_cloudwatch.egg-info/top_level.txt