Metadata-Version: 2.1
Name: celery-cloudwatch
Version: 2.0.0
Summary: A monitor for celery queues that reports to AWS CloudWatch
Home-page: https://github.com/3stack-software/celery-cloudwatch
Author: Nathan Muir
Author-email: ndmuir@gmail.com
License: MIT
Keywords: celery cloudwatch monitor stats
Platform: UNKNOWN
Classifier: Intended Audience :: Developers
Classifier: Intended Audience :: System Administrators
Classifier: License :: OSI Approved :: Apache Software License
Classifier: Programming Language :: Python :: 3
Classifier: Programming Language :: Python :: 3.6
Classifier: Programming Language :: Python :: 3.7
Requires-Python: >= 3.6
